{
  "type": "FeatureCollection",
  "name": "Комбинаты питания",
  "style": {
    "color": "blue",
    "radius": 6
  },
  "features": [
    {
      "type": "Feature",
      "id": "ebf5ab82-c7fa-42bc-8a95-e044cf46a163",
      "properties": {
        "name": "Комбинат питания г. Иркутска",
        "subcategory": "Комбинаты питания",
        "rating": "3.7",
        "site": "http://irkompit.ru",
        "hours": "Пн: с 08:00 до 12:00, Вт: с 08:00 до 12:00, Ср: с 08:00 до 12:00, Чт: с 08:00 до 12:00, Пт: с 08:00 до 12:00, Сб: выходной, Вс: выходной"
      },
      "geometry": {
        "type": "Point",
        "coordinates": [
          104.311196,
          52.261351
        ]
      }
    },
    {
      "type": "Feature",
      "id": "639d2cf4-da9d-4e02-8eb4-58a572c354b6",
      "properties": {
        "name": "Универсал-сервис, Компания",
        "subcategory": "Комбинаты питания",
        "rating": "nan",
        "site": "nan",
        "hours": "Пн: с 09:00 до 18:00, Вт: с 09:00 до 18:00, Ср: с 09:00 до 18:00, Чт: с 09:00 до 18:00, Пт: с 09:00 до 18:00, Сб: выходной, Вс: выходной"
      },
      "geometry": {
        "type": "Point",
        "coordinates": [
          104.289381,
          52.282031
        ]
      }
    },
    {
      "type": "Feature",
      "id": "f46c8e18-ee69-431f-b016-50cf363cf6cd",
      "properties": {
        "name": "Городской комбинат школьного питания",
        "subcategory": "Комбинаты питания",
        "rating": "2.0",
        "site": "http://xn----7sbc2aimje5bla.xn--p1ai/",
        "hours": "Пн: с 08:00 до 12:00, Вт: с 08:00 до 12:00, Ср: с 08:00 до 12:00, Чт: с 08:00 до 12:00, Пт: с 08:00 до 12:00, Сб: выходной, Вс: выходной"
      },
      "geometry": {
        "type": "Point",
        "coordinates": [
          107.650235,
          51.814449
        ]
      }
    }
  ]
}